{
	"Arabic": "العربية",
	"Amharic": "አማርኛ",
	"Belarusian": "Беларуская",
	"Bengali": "বাংলা",
	"Chinese": "中文",
	"Czech": "česky",
	"English": "English",
	"French": "français",
	"German": "Deutsch",
	"Hindi": "हिन्दी",
	"Italian": "Italiano",
	"Japanese": "日本語",
	"Korean": "한국어",
	"Kurdish": "Kurdî",
	"Persian": "فارسی",
	"Polish": "polski",
	"Russian": "русский язык",
	"Serbian": "српски језик",
	"Somali": "Soomaaliga",
	"Spanish": "español",
	"Sundanese": "Basa Sunda",
	"Swahili": "Kiswahili",
	"Turkish": "Türkçe",
	"Ukrainian": "українська",
	"Urdu": "اردو"
}
